weiyi/rwg.py
weiyi/std.py
weiyi-0.0.1.dist-info/METADATA
weiyi-0.0.1.dist-info/WHEEL
weiyi-0.0.1.dist-info/top_level.txt
weiyi-0.0.1.dist-info/RECORD
