Metadata-Version: 2.4
Name: weiyi
Version: 0.0.1
Summary: Future Instrument
Author-email: nzturn <nzturn@gmail.com>
Keywords: instrument
Classifier: Development Status :: 3 - Alpha
Classifier: Intended Audience :: Developers
Classifier: Programming Language :: Python :: 3
Requires-Python: >=3.8
